alignak_checks_nrpe/__init__.py
alignak_checks_nrpe-2.0.2.data/data/share/alignak/etc/arbiter/packs/nrpe/commands.cfg
alignak_checks_nrpe-2.0.2.data/data/share/alignak/etc/arbiter/packs/nrpe/groups.cfg
alignak_checks_nrpe-2.0.2.data/data/share/alignak/etc/arbiter/packs/nrpe/services-freebsd.cfg
alignak_checks_nrpe-2.0.2.data/data/share/alignak/etc/arbiter/packs/nrpe/services-linux.cfg
alignak_checks_nrpe-2.0.2.data/data/share/alignak/etc/arbiter/packs/nrpe/services-windows.cfg
alignak_checks_nrpe-2.0.2.data/data/share/alignak/etc/arbiter/packs/nrpe/templates.cfg
alignak_checks_nrpe-2.0.2.data/data/share/alignak/etc/arbiter/packs/resource.d/nrpe.cfg
alignak_checks_nrpe-2.0.2.data/data/share/alignak/etc/backend-json/nrpe/commands.json
alignak_checks_nrpe-2.0.2.data/data/share/alignak/etc/backend-json/nrpe/hostgroups.json
alignak_checks_nrpe-2.0.2.data/data/share/alignak/etc/backend-json/nrpe/hosts-templates.json
alignak_checks_nrpe-2.0.2.data/data/share/alignak/etc/backend-json/nrpe/servicegroups.json
alignak_checks_nrpe-2.0.2.data/data/share/alignak/etc/backend-json/nrpe/services-templates.json
alignak_checks_nrpe-2.0.2.data/data/share/alignak/etc/backend-json/nrpe/setup.sh
alignak_checks_nrpe-2.0.2.dist-info/LICENSE
alignak_checks_nrpe-2.0.2.dist-info/METADATA
alignak_checks_nrpe-2.0.2.dist-info/WHEEL
alignak_checks_nrpe-2.0.2.dist-info/top_level.txt
alignak_checks_nrpe-2.0.2.dist-info/RECORD
